MANIFEST.in
README.md
setup.cfg
setup.py
bluemix_service_discovery/__init__.py
bluemix_service_discovery/exceptions.py
bluemix_service_discovery/service_locator.py
bluemix_service_discovery/service_publisher.py
bluemix_service_discovery/utils.py
bluemix_service_discovery.egg-info/PKG-INFO
bluemix_service_discovery.egg-info/SOURCES.txt
bluemix_service_discovery.egg-info/dependency_links.txt
bluemix_service_discovery.egg-info/requires.txt
bluemix_service_discovery.egg-info/top_level.txt