Metadata-Version: 1.1
Name: bluemix-service-discovery
Version: 0.0.1
Summary: Python client for the Bluemix Service Discovery service
Home-page: https://github.com/IBM-Bluemix/service-discovery-client-python
Author: Jake Peyser
Author-email: jepeyser@us.ibm.com
License: Apache-2.0
Keywords: service-discovery service-registry microservices
Platform: UNKNOWN
Classifier: Development Status :: 4 - Beta
Classifier: Intended Audience :: Developers
Classifier: Topic :: Software Development :: Libraries :: Python Modules
Classifier: License :: OSI Approved :: Apache Software License
Classifier: Programming Language :: Python :: 2.7
Classifier: Programming Language :: Python :: 3.3
